sulfur_auth/__init__.py
sulfur_auth/sulfur.py
sulfur_auth-0.0.3.dist-info/METADATA
sulfur_auth-0.0.3.dist-info/WHEEL
sulfur_auth-0.0.3.dist-info/licenses/LICENSE
sulfur_auth-0.0.3.dist-info/RECORD
